{
  "location": "Dulzura, CA",
  "title": "Wine Tasting at Dulzura Vineyard & Winery",
  "date_start": "2026-01-10",
  "date_end": "2026-01-11",
  "summary": "We made our way southwest on more twisting, mountain roads. We stopped for a short run/hike, which ended up being a full-on bushwack before continuing on to our next Harvest Host destination, Dulzura Vineyad & Winery. There was a nice lot for us to park on surrounded by guava and key lime trees and set near a small creek. We enjoyed a wine tasting with one of the owners of the winery, where we sampled wine and listened to the history of his life and the property. <br><br> <b>-Helen<\/b>",
  "campsites": [
    "Dulzura Vineyard & Winery - Harvest Host"
  ],
  "photos": [
    {
      "caption": "Our van setup at Dulzura Vineyard & Winery.",
      "pth": "van_at_dulzura.webp"
    }
  ]
}
